{
  "project_info": {
    "project_number": "32903398845",
    "project_id": "binder-app-3b8de",
    "storage_bucket": "binder-app-3b8de.appspot.com"
  },
  "client": [
    {
      "client_info": {
        "mobilesdk_app_id": "1:32903398845:android:973311cc9f97c01a943ed4",
        "android_client_info": {
          "package_name": "com.example.chat_app"
        }
      },
      "oauth_client": [
        {
          "client_id": "32903398845-cv0pma5c611vvd4riguelddmbl07fl8g.apps.googleusercontent.com",
          "client_type": 3
        }
      ],
      "api_key": [
        {
          "current_key": "AIzaSyDvDYqP4XFvQtF2gB-nljIt-Q_pgRdoEGM"
        }
      ],
      "services": {
        "appinvite_service": {
          "other_platform_oauth_client": [
            {
              "client_id": "32903398845-cv0pma5c611vvd4riguelddmbl07fl8g.apps.googleusercontent.com",
              "client_type": 3
            }
          ]
        }
      }
    }
  ],
  "configuration_version": "1"
}